oligos_replacement/__init__.py
oligos_replacement/bed_assembly.py
oligos_replacement/check_outputs.py
oligos_replacement/little_functions.py
oligos_replacement/oligofile_correction.py
oligos_replacement/oligos_replacement.py
oligos_replacement/tests_replacement.py
tests/__init__.py
tests/test_oligo_file_correction.py
tests/test_oligo_replacement.py
oligos_replacement-1.0.8.dist-info/LICENSE
oligos_replacement-1.0.8.dist-info/METADATA
oligos_replacement-1.0.8.dist-info/WHEEL
oligos_replacement-1.0.8.dist-info/entry_points.txt
oligos_replacement-1.0.8.dist-info/top_level.txt
oligos_replacement-1.0.8.dist-info/RECORD
