Metadata-Version: 2.1
Name: oligos-replacement
Version: 1.0.8
Summary: replaces in a genome original sequences by new oligo sequences created for HiC Capture ssDNA
Home-page: https://gitbio.ens-lyon.fr/LBMC/GM/oligos-replacement
Author: Loqmen Anani
Author-email: loqmen.anani@ens-lyon.fr
Classifier: License :: OSI Approved :: GNU General Public License v3 (GPLv3)
Classifier: Programming Language :: Python :: 3
Classifier: Operating System :: OS Independent
License-File: LICENSE
Requires-Dist: pandas
